sinapsis_cotracker/src/sinapsis_cotracker/__init__.py
sinapsis_cotracker/src/sinapsis_cotracker/helpers/__init__.py
sinapsis_cotracker/src/sinapsis_cotracker/helpers/file_downloader.py
sinapsis_cotracker/src/sinapsis_cotracker/templates/__init__.py
sinapsis_cotracker/src/sinapsis_cotracker/templates/co_tracker_base.py
sinapsis_cotracker/src/sinapsis_cotracker/templates/co_tracker_offline.py
sinapsis_cotracker/src/sinapsis_cotracker/templates/co_tracker_offline_large.py
sinapsis_cotracker/src/sinapsis_cotracker/templates/co_tracker_online.py
sinapsis_cotracker/src/sinapsis_cotracker/templates/co_tracker_visualizer.py
sinapsis_rf_trackers/src/sinapsis_rf_trackers/__init__.py
sinapsis_rf_trackers/src/sinapsis_rf_trackers/helpers/__init__.py
sinapsis_rf_trackers/src/sinapsis_rf_trackers/helpers/tags.py
sinapsis_rf_trackers/src/sinapsis_rf_trackers/templates/__init__.py
sinapsis_rf_trackers/src/sinapsis_rf_trackers/templates/deepsort_tracker_inference.py
sinapsis_rf_trackers/src/sinapsis_rf_trackers/templates/rf_tracker_base.py
sinapsis_rf_trackers/src/sinapsis_rf_trackers/templates/sort_tracker_inference.py
sinapsis_supervision/src/sinapsis_supervision/__init__.py
sinapsis_supervision/src/sinapsis_supervision/templates/__init__.py
sinapsis_supervision/src/sinapsis_supervision/templates/byte_track.py
sinapsis_trackers-0.1.8.dist-info/licenses/LICENSE
sinapsis_trackers-0.1.8.dist-info/METADATA
sinapsis_trackers-0.1.8.dist-info/WHEEL
sinapsis_trackers-0.1.8.dist-info/top_level.txt
sinapsis_trackers-0.1.8.dist-info/RECORD
