Metadata-Version: 2.4
Name: sinapsis-trackers
Version: 0.1.8
Summary: Package for multi-object tracking using advanced algorithms and models.
Author-email: SinapsisAI <dev@sinapsis.tech>
Project-URL: Homepage, https://sinapsis.tech
Project-URL: Documentation, https://docs.sinapsis.tech/docs
Project-URL: Tutorials, https://docs.sinapsis.tech/tutorials
Project-URL: Repository, https://github.com/Sinapsis-AI/sinapsis-trackers.git
Requires-Python: >=3.10
License-File: LICENSE
Requires-Dist: sinapsis>=0.2.2
Provides-Extra: gradio-app
Requires-Dist: sinapsis[webapp]>=0.2.2; extra == "gradio-app"
Provides-Extra: all
Requires-Dist: sinapsis-cotracker[all]; extra == "all"
Requires-Dist: sinapsis-supervision[all]; extra == "all"
Requires-Dist: sinapsis-rf-trackers[all]; extra == "all"
Requires-Dist: sinapsis-trackers[cotracker,gradio-app]; extra == "all"
Provides-Extra: cotracker
Requires-Dist: cotracker; extra == "cotracker"
Dynamic: license-file
